kirjava.py
kirjava/__init__.py
kirjava/client.py
kirjava/utilities.py
kirjava-0.4.0.dist-info/LICENSE
kirjava-0.4.0.dist-info/METADATA
kirjava-0.4.0.dist-info/WHEEL
kirjava-0.4.0.dist-info/top_level.txt
kirjava-0.4.0.dist-info/RECORD
